{"IDN": "000020079", "001": "000020079", "002": "20161230", "005": "20161230201033", "008": "060222s1000------------r-----000-0-rum-d", "040": {"a": "IFIN-HH"}, "041": {"a": "rum"}, "080": {"a": "531"}, "1001": {"L": "000011598", "a": "Dragos, Lazar"}, "24510": {"a": "Principiile mecanici mediilor continue.", "c": "Lazar Dragos"}, "260": {"a": "Bucuresti, Editura Tehnica, 1983."}, "300": {"a": "509 P."}, "852": {"a": "70824", "c": "531"}, "CAT": {"a": "Sys", "c": "20100701", "h": "093653"}, "FMT": "BK", "LDR": "-----nam--22------i-4500", "LNG": "rum"}