{"IDN": "000004103", "001": "000004103", "002": "20161230", "005": "20161230201025", "008": "060222s1000------------r-----000-0-rum-d", "040": {"a": "IFIN-HH"}, "041": {"a": "rum"}, "1001": {"L": "000001864", "a": "Buzdugan, Gh."}, "24510": {"a": "Lucrari de laborator de rezistenta materialelor", "c": "Gh. buzdugan, m. blumenfeld"}, "260": {"a": "Bucuresti", "b": "Editura Institutul Politehnic", "c": "1953"}, "300": {"a": "88 P."}, "7001": {"L": "000002226", "a": "Blumenfefld, M."}, "852": {"a": "3848", "c": "539.4"}, "CAT": {"a": "Sys", "c": "20130128", "h": "125312"}, "FMT": "BK", "LDR": "-----nam--22------i-4500", "LNG": "rum"}