{"IDN": "000046637", "001": "000046637", "002": "20161230", "005": "20161230201046", "008": "060222s1000------------r-----000-0-rum-d", "040": {"a": "IFIN-HH"}, "041": {"a": "rum"}, "080": {"a": "539.4"}, "1001": {"L": "000018753", "a": "Mazilu, Panait"}, "24510": {"a": "Probleme de rezistenta materialelor", "b": "Indrumar de rezolvare si aplicatii speciale din constructii si constructii de masini vol. i", "c": "Panait mazilu, nicolae posea, eugen iordachescu"}, "260": {"a": "Bucuresti", "b": "Editura Tehnica", "c": "1969"}, "300": {"a": "462P."}, "7001": {"L": "000041461", "a": "Iordachescu, Eugen"}, "852": {"a": "30800", "c": "539.4"}, "CAT": {"a": "Sys", "c": "20130129", "h": "122554"}, "FMT": "BK", "LDR": "-----nam--22------i-4500", "LNG": "rum"}