{"IDN": "000052371", "001": "000052371", "002": "20161230", "005": "20161230201050", "008": "100628s1000------------r-----000-0-rus-d", "040": {"a": "IFIN-HH"}, "041": {"a": "rus"}, "080": {"a": "531"}, "1001": {"L": "000030045", "a": "Fillipova, B.V."}, "24510": {"a": "Fiziceskaia mehanika", "b": "vol. 2", "c": "B.V. Fillipova"}, "260": {"a": "Leningrad", "b": "Leningradskogo Universiteta", "c": "1976"}, "300": {"a": "177 p."}, "852": {"a": "43835", "c": "531"}, "CAT": {"a": "Sys", "c": "20100628", "h": "122150"}, "FMT": "BK", "LDR": "-----nam--22------u-4500", "LNG": "rus"}