{"IDN": "000055146", "001": "000055146", "002": "20161230", "005": "20161230201052", "008": "121107s1000------------r-----000-0-rus-d", "040": {"a": "IFIN-HH"}, "041": {"a": "rus"}, "080": {"a": "538.915"}, "1001": {"L": "000013646", "a": "Harrison, Walter A."}, "24510": {"a": "Elektronnaia struktura i svoistva tverdih tel", "b": "Fizika himiceskoi sviazi b dvuh tomah", "c": "Walter a. harrison"}, "260": {"a": "Moskva", "b": "Mir", "c": "1983"}, "300": {"a": "2 VOLUME"}, "500": {"a": "Titlul Original In Limba Engleza: Electric Structure And The Properties Of Solids, The Physics Of The Chemical Bond"}, "7861": {"a": "Volume 2", "h": "332p."}, "7871": {"a": "Volume 1", "h": "381p."}, "852": {"a": "71762", "c": "539.2"}, "CAT": {"a": "Sys", "c": "20121107", "h": "141420"}, "FMT": "BK", "LDR": "-----nam--22------u-4500", "LNG": "rus"}