{"IDN": "000029424", "001": "000029424", "002": "20161230", "005": "20161230201037", "008": "060222s1000------------r-----000-0-rus-d", "040": {"a": "IFIN-HH"}, "041": {"a": "rus"}, "080": {"a": "544.6+545.82:535.338(084)"}, "1001": {"L": "000031297", "a": "Taure, L.F."}, "24510": {"a": "Atlas spectralnih linii dlia analiza s pompsyu stiloskopa", "c": "L.f. taure"}, "260": {"a": "Riga", "b": "Akademii Hauk Latviiskoi Ssr", "c": "1957"}, "300": {"a": "163p."}, "852": {"a": "5045", "c": "545.33"}, "CAT": {"a": "Sys", "c": "20101130", "h": "144539"}, "FMT": "BK", "LDR": "-----nam--22------i-4500", "LNG": "rus"}