{"IDN": "000036264", "001": "000036264", "002": "20161230", "005": "20161230201040", "008": "060222s1000------------r-----000-0-rus-d", "040": {"a": "IFIN-HH"}, "041": {"a": "rus"}, "080": {"a": "530.162"}, "1001": {"L": "000035429", "a": "Martin, Paul"}, "24510": {"a": "Teoria sistem mnogih ceastit", "b": "Brounovskoe dvijenie kvantovogo ostilliatora", "c": "Paul martin, julian schwinger"}, "260": {"a": "Moskva", "b": "Inosctrannoi Literaturi", "c": "1962"}, "300": {"a": "168P."}, "500": {"a": "Titlul Original In Limba Engleza: Theory Of Many-particle Systems; Prownian Motion Of A Quantum Oscillator"}, "7001": {"L": "000041156", "a": "Schwinger, Julian"}, "852": {"a": "75485", "c": "539.141"}, "CAT": {"a": "Sys", "c": "20120418", "h": "122007"}, "FMT": "BK", "LDR": "-----nam--22------i-4500", "LNG": "rus"}