{"IDN": "000034258", "001": "000034258", "002": "20161230", "005": "20161230201040", "008": "060222s1000------------r-----000-0-ger-d", "040": {"a": "IFIN-HH"}, "041": {"a": "ger"}, "080": {"a": "536.75"}, "1001": {"L": "000019875", "a": "Munster, Arnold"}, "24510": {"a": "Satatistische thermodynamik. mit 193 textabbildungen.", "c": "Arnold munster"}, "260": {"a": "Berlin", "b": "Springer-verlag", "c": "1956"}, "300": {"a": "X + 852P."}, "852": {"a": "77675", "c": "536.7"}, "CAT": {"a": "Sys", "c": "20110603", "h": "125026"}, "FMT": "BK", "LDR": "-----nam--22------i-4500", "LNG": "ger"}