{"IDN": "000004419", "001": "000004419", "002": "20161230", "005": "20161230201025", "008": "060222s1000------------r-----000-0-eng-d", "100": {"L": "000002572", "a": "Clode, W./S.A./"}, "245": {"a": "Inportance of the determination of the weight of the tyroid gland and clinical biologic fact ors in the treatment of hyperthyroidism with i131"}, "260": {"a": "Lisboa, Comissao De Esstudos De Energia Nuclea R, 1959 8 P."}, "852": {"a": "13807"}, "FMT": "BK", "LDR": "-----nam--22------i-4500", "LNG": "eng"}