{"IDN": "000005559", "001": "000005559", "002": "20161230", "005": "20161230201026", "008": "060222s1000------------r-----000-0-eng-d", "040": {"a": "IFIN-HH"}, "080": {"a": "534.01"}, "1001": {"L": "000001278", "a": "Bickley, W. G."}, "24510": {"a": "An introduction to the theory vibrating systems.", "c": "W.g. bickely, a. talbot"}, "260": {"a": "Oxford, Clarendon Press, 1961. Xiv + 238 P."}, "7001": {"L": "000006253", "a": "Talbot, A."}, "852": {"a": "16353", "c": "534"}, "CAT": {"a": "Sys", "c": "20101007", "h": "092856"}, "FMT": "BK", "LDR": "-----nam--22------i-4500", "LNG": "eng"}