{"IDN": "000002809", "001": "000002809", "002": "20161230", "005": "20161230201025", "008": "060222s1000------------r-----000-0-eng-d", "080": {"a": "51"}, "100": {"L": "000001385", "a": "Bourbaki, N."}, "245": {"a": "Elements de mathematique. premiere partie: les structures fondamentales de l`analyse. chap.x"}, "260": {"a": "Paris, Hermann Et C-ie, 1947-1953"}, "490": {"a": "Actualites Scientifiques Et Industrielles."}, "852": {"a": "10660"}, "FMT": "BK", "LDR": "-----nam--22------i-4500", "LNG": "eng"}