{"IDN": "000020475", "001": "000020475", "002": "20161230", "005": "20161230201033", "008": "060222s1000------------r-----000-0-eng-d", "020": {"a": "155899016x"}, "040": {"a": "IFIN-HH"}, "080": {"a": "621.179.15(061.3)"}, "1001": {"L": "000034046", "a": "Clarke, Roy"}, "24510": {"a": "Synchrotron radiation in materials research", "b": "Volume 143 materials research society symposium proceedings. symposium held november 28-30,1988, boston, massachusetts, usa.", "c": "Roy clarke, john gland, john h. weaver (eds.)"}, "260": {"a": "Pittsburg, Pennsylvania", "b": "Materials Research Society", "c": "1988"}, "300": {"a": "304 P."}, "490": {"a": "Materials Research Society Symposium Proceedings"}, "7001": {"L": "000040721", "a": "Weaver, John H.", "e": "Ed."}, "852": {"a": "49226", "c": "539"}, "CAT": {"a": "Sys", "c": "20111012", "h": "145142"}, "FMT": "BK", "LDR": "-----nam--22------i-4500", "LNG": "eng"}