{"IDN": "000023094", "001": "000023094", "002": "20161230", "005": "20161230201034", "008": "060222s1000------------r-----000-0-eng-d", "040": {"a": "IFIN-HH"}, "080": {"a": "539.143.43(043)"}, "1001": {"L": "000013861", "a": "Jackson, Darrell Richard"}, "24510": {"a": "A frequency-selective limiter using nuclear magnetic resonance", "b": "Dissertation", "c": "Darrell richard jackson"}, "260": {"a": "Ann Arbor, Michigan,", "b": "University Microfilms, Inc.", "c": "1966"}, "300": {"a": "XII + 140 P."}, "852": {"a": "35578", "c": "539.143.43"}, "CAT": {"a": "Sys", "c": "20120507", "h": "165709"}, "FMT": "BK", "LDR": "-----nam--22------i-4500", "LNG": "eng"}