{"IDN": "000025706", "001": "000025706", "002": "20161230", "005": "20170208133254", "008": "060222s1000------------r-----000-0-eng-d", "245": {"a": "The international encyclopedia of physical chemistry and chemical physics. Topic 11. The ideal crytstalline state. Vol.2. Elementary theory of metals"}, "260": {"a": "Oxford", "b": "Pergamon Press", "c": "1967"}, "700": {"L": "000000510", "a": "Donovan, B."}, "852": {"a": "11315"}, "CAT": {"a": "SYS", "c": "20170208", "h": "133254"}, "FMT": "BK", "LDR": "-----nam--22------i-4500", "LNG": "eng"}