{"IDN": "000022620", "001": "000022620", "002": "20161230", "005": "20161230201034", "008": "060222s1000------------r-----000-0-rus-d", "040": {"a": "IFIN-HH"}, "041": {"a": "rus"}, "080": {"a": "539.23:621.3.049.77"}, "1101": {"L": "000029903", "a": "Akademia Nauk SSSR"}, "24510": {"a": "Poluprovodnikovieplenki dlia mikroelektroniki"}, "260": {"a": "Novosibirsk", "b": "Nauka", "c": "1977"}, "300": {"a": "245P."}, "852": {"a": "46232", "c": "539.23"}, "CAT": {"a": "Sys", "c": "20121218", "h": "141007"}, "FMT": "BK", "LDR": "-----nam--22------i-4500", "LNG": "rus"}