{"IDN": "000010863", "001": "000010863", "002": "20161230", "005": "20161230201029", "008": "060222s1000------------r-----000-0-eng-d", "080": {"a": "519.4"}, "100": {"L": "000006677", "a": "Bredon, Glen E."}, "245": {"a": "Introduction to compact transformation groups"}, "260": {"a": "New York, Academic Press, 1972 Xi + 456 P."}, "490": {"a": "Pure And Applied Mathenatics", "v": "vol. 46"}, "852": {"a": "13669"}, "CAT": {"a": "Sys", "c": "20080401", "h": "133959"}, "FMT": "BK", "LDR": "-----nam--22------i-4500", "LNG": "eng"}