{"IDN": "000008093", "001": "000008093", "002": "20161230", "005": "20161230201027", "008": "060222s1000------------r-----000-0-eng-d", "100": {"L": "000005043", "a": "Cohen-tannoudji, G., Morel, A.And Navelet, H."}, "245": {"a": "Kinematical singularities, crossing matrix and kinematical constraints for two-body helicity amplitudes"}, "260": {"a": "Saclau, Centre D Etudes Nucleaires, 1967"}, "490": {"a": "132p."}, "852": {"a": "530.1"}, "FMT": "BK", "LDR": "-----nam--22------i-4500", "LNG": "eng"}