{"IDN": "000015552", "001": "000015552", "002": "20161230", "005": "20161230201031", "008": "060222s1000------------r-----000-0-fre-d", "040": {"a": "IFIN-HH"}, "041": {"a": "fre"}, "080": {"a": "621.039.58"}, "1001": {"L": "000009728", "a": "Charuau, Jean"}, "24510": {"a": "Optimisation de la detection des aerosols radiactifs dans un local", "b": "Seminaires sfrp - pierre latte, 22 au 26 mars 1982 avec le concours du centre technique de reference en ventilation et epuration necleaires (institut de protection et de surete nucleaire)", "c": "Jean charuau"}, "260": {"a": "Paris", "b": "Societe Francause De Radioprotection", "c": "1982"}, "300": {"a": "/PAG.DIF./"}, "852": {"a": "72827", "c": "539.1.07:539.1.08"}, "CAT": {"a": "Sys", "c": "20111031", "h": "130544"}, "FMT": "BK", "LDR": "-----nam--22------i-4500", "LNG": "fre"}