{"IDN": "000008628", "001": "000008628", "002": "20161230", "005": "20161230201027", "008": "060222s1000------------r-----000-0-eng-d", "040": {"a": "IFIN-HH"}, "080": {"a": "541:539.124.14"}, "1001": {"L": "000005326", "a": "Danner, Joseph C."}, "24510": {"a": "A study of the spin-spin exchange interaction between free radicals in solution", "b": "Dissertation", "c": "Joseph c. danner"}, "260": {"a": "Ann Arbor, Michigan", "b": "University Microfilms, Inc.", "c": "1966"}, "300": {"a": "VIII+145P."}, "852": {"a": "29636", "c": "539.12"}, "CAT": {"a": "Sys", "c": "20111116", "h": "165054"}, "FMT": "BK", "LDR": "-----nam--22------i-4500", "LNG": "eng"}