{"leader": "-----nam--22------i-4500", "fields": [{"IDN": {"subfields": [], "indicators": [" ", " "], "tag": "IDN", "value": "000020338"}}, {"001": {"subfields": [], "indicators": [" ", " "], "tag": "001", "value": "000020338"}}, {"002": {"subfields": [], "indicators": [" ", " "], "tag": "002", "value": "20161230"}}, {"005": {"subfields": [], "indicators": [" ", " "], "tag": "005", "value": "20170113231047"}}, {"008": {"subfields": [], "indicators": [" ", " "], "tag": "008", "value": "060222s1000------------r-----000-0-eng-d"}}, {"080": {"subfields": [{"code": "a", "value": "621.039.58"}], "indicators": [" ", " "], "tag": "080"}}, {"245": {"subfields": [{"code": "a", "value": "The consequences of the Chernobyl nuclear accident in Greece"}], "indicators": [" ", " "], "tag": "245"}}, {"260": {"subfields": [{"code": "a", "value": "Athens"}, {"code": "b", "value": "Greek Atomic Energy Commission"}, {"code": "c", "value": "1986"}], "indicators": [" ", " "], "tag": "260"}}, {"300": {"subfields": [{"code": "a", "value": "VII + 80 p"}], "indicators": [" ", " "], "tag": "300"}}, {"852": {"subfields": [{"code": "a", "value": "73552"}], "indicators": [" ", " "], "tag": "852"}}, {"CAT": {"subfields": [{"code": "a", "value": "SYS"}, {"code": "c", "value": "20170113"}, {"code": "h", "value": "231047"}], "indicators": [" ", " "], "tag": "CAT"}}, {"FMT": {"subfields": [], "indicators": [" ", " "], "tag": "FMT", "value": "BK"}}, {"LDR": {"subfields": [], "indicators": [" ", " "], "tag": "LDR", "value": "-----nam--22------i-4500"}}, {"LNG": {"subfields": [], "indicators": [" ", " "], "tag": "LNG", "value": "eng"}}]}