{"leader": "-----nam--22------i-4500", "fields": [{"IDN": {"subfields": [], "indicators": [" ", " "], "tag": "IDN", "value": "000012726"}}, {"001": {"subfields": [], "indicators": [" ", " "], "tag": "001", "value": "000012726"}}, {"002": {"subfields": [], "indicators": [" ", " "], "tag": "002", "value": "20161230"}}, {"005": {"subfields": [], "indicators": [" ", " "], "tag": "005", "value": "20161230201029"}}, {"008": {"subfields": [], "indicators": [" ", " "], "tag": "008", "value": "060222s1000------------r-----000-0-eng-d"}}, {"100": {"subfields": [{"code": "a", "value": "Carrigan, Richard A.Jr"}], "indicators": [" ", " "], "tag": "100", "value": null}}, {"245": {"subfields": [{"code": "a", "value": "Magnetic monopole bibliography 1973 - 1976"}], "indicators": [" ", " "], "tag": "245"}}, {"260": {"subfields": [{"code": "a", "value": "Batavia, Fermi National Accelerator Laboratory 1977"}], "indicators": [" ", " "], "tag": "260"}}, {"490": {"subfields": [{"code": "a", "value": "Fermilab - 77/42"}], "indicators": [" ", " "], "tag": "490"}}, {"852": {"subfields": [{"code": "a", "value": "539.12.14(01)(047.3)"}], "indicators": [" ", " "], "tag": "852"}}, {"FMT": {"subfields": [], "indicators": [" ", " "], "tag": "FMT", "value": "BK"}}, {"LDR": {"subfields": [], "indicators": [" ", " "], "tag": "LDR", "value": "-----nam--22------i-4500"}}, {"LNG": {"subfields": [], "indicators": [" ", " "], "tag": "LNG", "value": "eng"}}]}