{"leader": "-----nam--22------u-4500", "fields": [{"IDN": {"subfields": [], "indicators": [" ", " "], "tag": "IDN", "value": "000054758"}}, {"001": {"subfields": [], "indicators": [" ", " "], "tag": "001", "value": "000054758"}}, {"002": {"subfields": [], "indicators": [" ", " "], "tag": "002", "value": "20161230"}}, {"005": {"subfields": [], "indicators": [" ", " "], "tag": "005", "value": "20210312045059"}}, {"008": {"subfields": [], "indicators": [" ", " "], "tag": "008", "value": "120605s1000------------r-----000-0-rum-d"}}, {"040": {"subfields": [{"code": "a", "value": "IFIN-HH"}], "indicators": [" ", " "], "tag": "040"}}, {"041": {"subfields": [{"code": "a", "value": "rum"}], "indicators": [" ", " "], "tag": "041"}}, {"080": {"subfields": [{"code": "a", "value": "539.171"}], "indicators": [" ", " "], "tag": "080"}}, {"100": {"subfields": [{"code": "a", "value": "Ivascu, Marin"}], "indicators": ["1", " "], "tag": "100", "value": null}}, {"245": {"subfields": [{"code": "a", "value": "Studiul imprastierii particulelor alfa de joasa energie pe nuclee par-pare usoare si medii (20ne; 23mg; 32s; 40a; 48ti; 54fe; 58, 60ni, si 66,68zn)"}, {"code": "b", "value": "Autoreferatul tezei"}, {"code": "c", "value": "Marin Ivascu"}], "indicators": ["1", "0"], "tag": "245"}}, {"260": {"subfields": [{"code": "a", "value": "Bucuresti"}, {"code": "b", "value": "Institutul De Fizica Atomica"}, {"code": "c", "value": "1968"}], "indicators": [" ", " "], "tag": "260"}}, {"300": {"subfields": [{"code": "a", "value": "28P"}], "indicators": [" ", " "], "tag": "300"}}, {"502": {"subfields": [{"code": "a", "value": "Conducator Stiintific: Acad.Prof. Horia Hulubei"}], "indicators": [" ", " "], "tag": "502"}}, {"852": {"subfields": [{"code": "a", "value": "29508"}, {"code": "c", "value": "539.17"}], "indicators": [" ", " "], "tag": "852"}}, {"CAT": {"subfields": [{"code": "a", "value": "SYS"}, {"code": "c", "value": "20210312"}, {"code": "h", "value": "045059"}], "indicators": [" ", " "], "tag": "CAT"}}, {"FMT": {"subfields": [], "indicators": [" ", " "], "tag": "FMT", "value": "BK"}}, {"LDR": {"subfields": [], "indicators": [" ", " "], "tag": "LDR", "value": "-----nam--22------u-4500"}}, {"LNG": {"subfields": [], "indicators": [" ", " "], "tag": "LNG", "value": "rum"}}]}