{"leader": "-----nam--22------i-4500", "fields": [{"IDN": {"subfields": [], "indicators": [" ", " "], "tag": "IDN", "value": "000030883"}}, {"001": {"subfields": [], "indicators": [" ", " "], "tag": "001", "value": "000030883"}}, {"002": {"subfields": [], "indicators": [" ", " "], "tag": "002", "value": "20161230"}}, {"005": {"subfields": [], "indicators": [" ", " "], "tag": "005", "value": "20170102002705"}}, {"008": {"subfields": [], "indicators": [" ", " "], "tag": "008", "value": "060222s1000------------r-----000-0-eng-d"}}, {"080": {"subfields": [{"code": "a", "value": "577.3:539.12.04"}], "indicators": [" ", " "], "tag": "080"}}, {"100": {"subfields": [{"code": "a", "value": "Mathe, Georges"}], "indicators": [" ", " "], "tag": "100", "value": null}}, {"245": {"subfields": [{"code": "a", "value": "L`applaise myelo-lymphoide de l`irradiation totale. expression, applications, traitement"}], "indicators": [" ", " "], "tag": "245"}}, {"260": {"subfields": [{"code": "a", "value": "Paris"}, {"code": "b", "value": "Gauthier-Villars"}, {"code": "c", "value": "1965"}], "indicators": [" ", " "], "tag": "260"}}, {"300": {"subfields": [{"code": "a", "value": "VIII + 245p"}], "indicators": [" ", " "], "tag": "300"}}, {"700": {"subfields": [{"code": "a", "value": "Schwarzenberg, Leon"}], "indicators": [" ", " "], "tag": "700", "value": null}}, {"852": {"subfields": [{"code": "a", "value": "24188"}], "indicators": [" ", " "], "tag": "852"}}, {"CAT": {"subfields": [{"code": "a", "value": "SYS"}, {"code": "c", "value": "20170102"}, {"code": "h", "value": "002705"}], "indicators": [" ", " "], "tag": "CAT"}}, {"FMT": {"subfields": [], "indicators": [" ", " "], "tag": "FMT", "value": "BK"}}, {"LDR": {"subfields": [], "indicators": [" ", " "], "tag": "LDR", "value": "-----nam--22------i-4500"}}, {"LNG": {"subfields": [], "indicators": [" ", " "], "tag": "LNG", "value": "eng"}}]}