{"IDN": "000027140", "001": "000027140", "002": "20161230", "005": "20161230201036", "008": "060222s1000------------r-----000-0-eng-d", "040": {"a": "IFIN-HH"}, "080": {"a": "536.7:538.913"}, "1001": {"L": "000032226", "a": "Kocinski, Jerzy"}, "24510": {"a": "Critical scattering theory", "b": "An introduction", "c": "Jerzy kocinski; leszek wojtczak"}, "260": {"a": "Warszawa", "b": "Pwn-polish Scientific Publishing", "c": "1978"}, "300": {"a": "X + 227P."}, "7001": {"L": "000032676", "a": "Wojtczak, Leszek"}, "852": {"a": "46148", "c": "536.7"}, "CAT": {"a": "Sys", "c": "20110531", "h": "125938"}, "FMT": "BK", "LDR": "-----nam--22------i-4500", "LNG": "eng"}