{"IDN": "000029414", "001": "000029414", "002": "20161230", "005": "20170111001619", "008": "060222s1000------------r-----000-0-eng-d", "080": {"a": "530.1"}, "100": {"L": "000016839", "a": "Kummel, H."}, "245": {"a": "Equations for linked clusters and Brueckner-Bethe theory"}, "260": {"a": "Ruhr, Bochum", "b": "Institut Fur Theoretische Physik", "c": "1972"}, "300": {"a": "19 p.+10 Fig."}, "700": {"L": "000042400", "a": "Luhrmann, K. H."}, "852": {"a": "36867"}, "CAT": {"a": "SYS", "c": "20170111", "h": "001619"}, "FMT": "BK", "LDR": "-----nam--22------i-4500", "LNG": "eng"}