{"IDN": "000055087", "001": "000055087", "002": "20161230", "005": "20161230201052", "008": "121031s1000------------r-----000-0-rus-d", "040": {"a": "IFIN-HH"}, "041": {"a": "rus"}, "080": {"a": "539.2"}, "1001": {"L": "000035437", "a": "Vonsovskogo, S.V."}, "24510": {"a": "Kvantovie kristalli", "b": "Sbornik statei", "c": "S.v. vonsovskogo"}, "260": {"a": "Moskva", "b": "Mir", "c": "1975"}, "300": {"a": "273P."}, "490": {"a": "Novosti Fiziki Tverdogo Tela", "v": "Vipusk 4"}, "852": {"a": "48196", "c": "539.2"}, "CAT": {"a": "Sys", "c": "20121031", "h": "130450"}, "FMT": "BK", "LDR": "-----nam--22------u-4500", "LNG": "rus"}