{"IDN": "000054346", "001": "000054346", "002": "20161230", "005": "20161230201051", "008": "111123s1000------------r-----000-0-rus-d", "040": {"a": "IFIN-HH"}, "041": {"a": "rus"}, "080": {"a": "539.12"}, "1001": {"L": "000034570", "a": "Pomeranciuk, I.Ia."}, "24510": {"a": "Sobranie naucinih trudov v treh tomah", "b": "Ii fizika elementarnih ceastit. elektromagnitnir i clabie vzaimodeistvia", "c": "I.ia. pomeranciuk"}, "260": {"a": "Moskva", "b": "Nauka", "c": "1972"}, "300": {"a": "296P."}, "852": {"a": "39373", "c": "539.12"}, "CAT": {"a": "Sys", "c": "20111123", "h": "120355"}, "FMT": "BK", "LDR": "-----nam--22------u-4500", "LNG": "rus"}