{"IDN": "000003292", "001": "000003292", "002": "20161230", "005": "20170212000706", "008": "060222s1000------------r-----000-0-eng-d", "100": {"L": "000001722", "a": "Ballard, S. S."}, "245": {"a": "Physics principles"}, "260": {"a": "Princepton", "b": "D.Van Nostrand", "c": "1957"}, "300": {"a": "IV+743 p."}, "490": {"a": "(4-th Printing)"}, "700": {"L": "000042844", "a": "Slack, E. P."}, "CAT": {"a": "SYS", "c": "20170212", "h": "000706"}, "FMT": "BK", "LDR": "-----nam--22------i-4500", "LNG": "eng"}