{"IDN": "000043723", "001": "000043723", "002": "20161230", "005": "20161230201044", "008": "060222s1000------------r-----000-0-eng-d", "020": {"a": "3540110984"}, "040": {"a": "IFIN-HH"}, "080": {"a": "539.184.2:538.91"}, "1001": {"L": "000036713", "a": "Matsubara, T."}, "24510": {"a": "The structure and properties of matter", "b": "With contributions by t. matsubara, h. matsuda, r. murao, t. tsuneto, f. yonezawa", "c": "T. matsubara (ed.)"}, "260": {"a": "Berlin", "b": "Springer-verlag", "c": "1982"}, "300": {"a": "XI+446P."}, "490": {"a": "Springer Series In Solid-state Sciences", "v": "Vol. 28"}, "852": {"a": "46526", "c": "539.2"}, "CAT": {"a": "Sys", "c": "20121029", "h": "155207"}, "FMT": "BK", "LDR": "-----nam--22------i-4500", "LNG": "eng"}