{"IDN": "000056302", "001": "000056302", "002": "20161230", "005": "20161230201052", "008": "150327s1000------------r-----000-0-rus-d", "040": {"a": "IFIN-HH"}, "041": {"a": "rus"}, "080": {"a": "53(091)"}, "1001": {"L": "000039340", "a": "Dorfman, Ia.G."}, "24510": {"a": "Vsemirnaia istoria fiziki s naceala xix do seredini xx vv.", "c": "Ia.g. dorfman"}, "260": {"a": "Moskva", "b": "Nauka", "c": "1979"}, "300": {"a": "317P."}, "852": {"a": "48593", "c": "53"}, "CAT": {"a": "Sys", "c": "20150327", "h": "114237"}, "FMT": "BK", "LDR": "-----nam--22------u-4500", "LNG": "rus"}