{"IDN": "000007704", "001": "000007704", "002": "20161230", "005": "20161230201027", "008": "060222s1000------------r-----000-0-eng-d", "040": {"a": "IFIN-HH"}, "080": {"a": "53:62"}, "100 1": {"L": "000004300", "a": "Beiser, Arthur"}, "24510": {"a": "Modern technical physics", "c": "Arthur beiser"}, "260": {"a": "Reading, Massachusetts", "b": "Addison-weley Publ.Co", "c": "1966"}, "300": {"a": "706 P."}, "852": {"a": "24457", "c": "53"}, "CAT": {"a": "Sys", "c": "20150218", "h": "132518"}, "FMT": "BK", "LDR": "-----nam--22------i-4500", "LNG": "eng"}