{"IDN": "000045240", "001": "000045240", "002": "20161230", "005": "20161230201044", "008": "060222s1000------------r-----000-0-eng-d", "040": {"a": "IFIN-HH"}, "080": {"a": "53"}, "1001": {"L": "000017995", "a": "Brittin, Wesley E./S.A/"}, "24510": {"a": "Topics in modern physics. a tribute to edward u. condon", "c": "Wesley e.brittin, halis odabasi (eds.)"}, "260": {"a": "London", "b": "Adam Hilger", "c": "1970"}, "300": {"a": "XXXIII + 360P."}, "7001": {"L": "000036218", "a": "Odabasi, Halis", "e": "Ed."}, "852": {"a": "37098", "c": "53"}, "CAT": {"a": "Sys", "c": "20150316", "h": "093335"}, "FMT": "BK", "LDR": "-----nam--22------i-4500", "LNG": "eng"}