{"IDN": "000056371", "001": "000056371", "002": "20161230", "005": "20161230201052", "008": "150811s1000------------r-----000-0-rus-d", "040": {"a": "IFIN-HH"}, "041": {"a": "rus"}, "080": {"a": "53"}, "1001": {"L": "000030110", "a": "Landau, L. D."}, "24510": {"a": "Sobranie trudov vol. 2", "c": "L.d. landau"}, "260": {"a": "Moskva", "b": "Nauka", "c": "1969"}, "300": {"a": "449P."}, "852": {"a": "75340", "c": "53"}, "CAT": {"a": "Sys", "c": "20150811", "h": "160615"}, "FMT": "BK", "LDR": "-----nam--22------u-4500", "LNG": "rus"}