{"IDN": "000056936", "001": "000056936", "002": "20201027", "005": "20201027065420", "008": "201027s1000------------r-----000-0-eng-d", "040": {"a": "IFIN-HH"}, "041": {"a": "eng"}, "1001": {"L": "000031644", "a": "Trache, Livius"}, "24510": {"a": "Exotic Nuclei and Nuclear Particle Astrophysics (V). From Nuclei to Stars.", "c": "Livius Trache, Daniela Chesneanu, Calin Alexandru Ur (eds.)"}, "260": {"a": "Melville,New York.", "b": "AIP", "c": "2015"}, "300": {"a": "449 p."}, "500": {"a": "Donatie Misicu Serban"}, "7001": {"L": "000031697", "a": "Ur, Calin Alexandru"}, "852": {"a": "82862", "c": "061.3"}, "CAT": {"a": "SYS", "c": "20201027", "h": "065420"}, "FMT": "BK", "LDR": "-----nam--22------u-4500", "LNG": "eng"}