{"IDN": "000042481", "001": "000042481", "002": "20161230", "005": "20161230201043", "008": "060222s1000------------r-----000-0-eng-d", "100": {"L": "000023906", "a": "Spiegel,Murray R."}, "245": {"a": "Vector analysis and an introduction to tensor analysis"}, "260": {"a": "New York, Schaum Publ.Co.,1959. 225 P."}, "490": {"a": "Schaum's Outline Series"}, "852": {"a": "27719", "c": "512.94:512.972"}, "CAT": {"a": "Sys", "c": "20080526", "h": "113546"}, "FMT": "BK", "LDR": "-----nam--22------i-4500", "LNG": "eng"}