{"IDN": "000026198", "001": "000026198", "002": "20161230", "005": "20161230201036", "008": "060222s1000------------r-----000-0-eng-d", "040": {"a": "IFIN-HH"}, "080": {"a": "519.283:338:658.15"}, "1001": {"L": "000015394", "a": "Karlin, Samuel"}, "24510": {"a": "Mathematical methods and theory in games, programming and economics", "b": "Volume i matrix games, programming, and mathematical economics", "c": "Samuel karlin"}, "260": {"a": "London", "b": "Pergamon Press", "c": "1959"}, "300": {"a": "X + 433P."}, "490": {"a": "Addison-wesley Series In Statistics"}, "852": {"a": "13229", "c": "519.283"}, "CAT": {"a": "Sys", "c": "20130806", "h": "113258"}, "FMT": "BK", "LDR": "-----nam--22------i-4500", "LNG": "eng"}