{"IDN": "000034991", "001": "000034991", "002": "20161230", "005": "20161230201040", "008": "060222s1000------------r-----000-0-eng-d", "040": {"a": "IFIN-HH"}, "080": {"a": "519.4"}, "1001": {"L": "000020210", "a": "Murnaghan, Francis D."}, "24510": {"a": "The unitary and rotation groups.", "c": "Francis d. murnaghan"}, "260": {"a": "Washington, D.C.", "b": "Spartan Books", "c": "1962"}, "300": {"a": "VII+151P."}, "490": {"a": "Lectures On Applied Mathematics."}, "852": {"a": "33682", "c": "519.4/5"}, "CAT": {"a": "Sys", "c": "20130812", "h": "162005"}, "FMT": "BK", "LDR": "-----nam--22------i-4500", "LNG": "eng"}