{"IDN": "000021152", "001": "000021152", "002": "20161230", "005": "20161230201034", "008": "060222s1000------------r-----000-0-eng-d", "040": {"a": "IFIN-HH"}, "080": {"a": "53.01"}, "1001": {"L": "000012800", "a": "Hutten, Ernest H."}, "24510": {"a": "The language of modern physics. an introduction to the philosophy of science", "c": "Ernest h. hutten"}, "260": {"a": "London", "b": "George Allen & Unwin Ltd.", "c": "1956"}, "300": {"a": "278 P."}, "852": {"a": "12038", "c": "53.01"}, "CAT": {"a": "Sys", "c": "20151012", "h": "120857"}, "FMT": "BK", "LDR": "-----nam--22------i-4500", "LNG": "eng"}