{"IDN": "000018020", "001": "000018020", "002": "20161230", "005": "20170211161350", "008": "060222s1000------------r-----000-0-eng-d", "080": {"a": "62.52"}, "245": {"a": "Elektronische und magnetische steuerungen und regelungen in der antriebstechnik. Zweite verbesserte auflage"}, "260": {"a": "Wuppertal U.Berlin", "b": "V.D.E.Verlag", "c": "1955"}, "300": {"a": "124 p."}, "710": {"L": "000042841", "a": "Wissenschaftlichen Ausschuss Des V.D.E."}, "852": {"a": "12933"}, "CAT": {"a": "SYS", "c": "20170211", "h": "161350"}, "FMT": "BK", "LDR": "-----nam--22------i-4500", "LNG": "eng"}