{"IDN": "000045526", "001": "000045526", "002": "20161230", "005": "20170105164955", "008": "060222s1000------------r-----000-0-eng-d", "040": {"a": "IFIN-HH"}, "080": {"a": "53"}, "1001": {"L": "000025285", "a": "Trigg, George L."}, "24510": {"a": "Crucial experiments in modern physics", "c": "George L. Trigg"}, "260": {"a": "New York", "b": "Van Nostrand Reinhold Company", "c": "1971"}, "300": {"a": "IX + 141 p."}, "490": {"a": "Van Nostrand Momentum Books", "v": "Book No.23"}, "852": {"a": "20430", "c": "539"}, "CAT": {"a": "SYS", "c": "20170105", "h": "164955"}, "FMT": "BK", "LDR": "-----nam--22------i-4500", "LNG": "eng"}