{"IDN": "000044396", "001": "000044396", "002": "20161230", "005": "20161230201044", "008": "060222s1000------------r-----000-0-eng-d", "100": {"L": "000024834", "a": "Tricomi,F.G."}, "24510": {"a": "Integral equations"}, "260": {"a": "New York, Academic Press, 1954,"}, "490": {"a": "Pure and Applied Mathematics", "v": "vol. V"}, "700": {"L": "000024834", "a": "Tricomi,F.G."}, "852": {"a": "13669"}, "CAT": {"a": "Sys", "c": "20080401", "h": "113142"}, "FMT": "BK", "LDR": "-----nam--22------i-4500", "LNG": "eng"}