{"IDN": "000032288", "001": "000032288", "002": "20161230", "005": "20161230201039", "008": "060222s1000------------r-----000-0-eng-d", "080": {"a": "512.831"}, "100": {"L": "000018775", "a": "Mikelsson, J. And Niederle, J."}, "245": {"a": "On integrability of discrete representations of lie algebra u (p,q)."}, "260": {"a": "Prague, Inst.Of Ph., 1973. 11p."}, "852": {"a": "37208", "c": "512.831"}, "CAT": {"a": "Sys", "c": "20080522", "h": "123749"}, "FMT": "BK", "LDR": "-----nam--22------i-4500", "LNG": "eng"}