{"IDN": "000023365", "001": "000023365", "002": "20161230", "005": "20161230201035", "008": "060222s1000------------r-----000-0-eng-d", "080": {"a": "543.51(043)"}, "100": {"L": "000014020", "a": "Jerome, Dominique Y.Et Slodzian, Georges"}, "245": {"a": "Utilisation du microanalyseur ionique en geochimie. application a la meteorite de juvinas. these"}, "260": {"a": "Paris, Universite Paris, 1971, /538-548p./"}, "490": {"a": "Bulletin De La Societe Francais De Mineralogie Et De Cristallographie"}, "852": {"a": "40474"}, "FMT": "BK", "LDR": "-----nam--22------i-4500", "LNG": "eng"}