{"IDN": "000033753", "001": "000033753", "002": "20161230", "005": "20161230201039", "008": "060222s1000------------r-----000-0-eng-d", "020": {"a": "0444417907"}, "040": {"a": "IFIN-HH"}, "080": {"a": "539.196(061.3)"}, "1001": {"L": "000019588", "a": "Nell, Louis"}, "24510": {"a": "Nonlinear behaviour of molecules, atoms and ions in electric, magnetic or electromagnetic fields", "b": "Proceedings of the 31st international meeting of the societe de chimie physique abbaye de fontevraud 25-28 september 1978", "c": "Louis nell (ed.)"}, "260": {"a": "Amsterdam", "b": "Elsevier Scientific Publishing Comupany", "c": "1979"}, "300": {"a": "XX+515P."}, "852": {"a": "48009", "c": "539.19"}, "CAT": {"a": "Sys", "c": "20120716", "h": "163717"}, "FMT": "BK", "LDR": "-----nam--22------i-4500", "LNG": "eng"}