{"IDN": "000043133", "001": "000043133", "002": "20161230", "005": "20161230201043", "008": "060222s1000------------r-----000-0-eng-d", "040": {"a": "IFIN-HH"}, "080": {"a": "537.312.62"}, "1001": {"L": "000033027", "a": "Parks, R.D."}, "24510": {"a": "Superconductivity.", "c": "R.d.parks"}, "260": {"a": "New York", "b": "Marcel Dekker, Inc.", "c": "1969"}, "300": {"a": "IN TWO VOLUMES."}, "7871": {"a": "Vol. 2", "h": "/644p./1412p."}, "852": {"a": "77666", "c": "537:538"}, "CAT": {"a": "Sys", "c": "20110629", "h": "162355"}, "FMT": "BK", "LDR": "-----nam--22------i-4500", "LNG": "eng"}