{"IDN": "000056045", "001": "000056045", "002": "20161230", "005": "20161230201052", "008": "141204s1000------------r-----000-0-eng-d", "020": {"a": "096014482X"}, "040": {"a": "IFIN-HH"}, "080": {"a": "30.12:523:629.12(082.1)"}, "1001": {"L": "000038387", "a": "Zapffe, Carl Andrew"}, "24510": {"a": "A reminder on e=mc2", "b": "With an appendix on astronautic interferometry", "c": "Carl andrew zapffe"}, "260": {"a": "Brainerd, Minnesota", "b": "Lakeland Color Oress, Inc.", "c": "/F.An/"}, "300": {"a": "208P."}, "852": {"a": "71211", "c": "523"}, "CAT": {"a": "Sys", "c": "20141204", "h": "152200"}, "FMT": "BK", "LDR": "-----nam--22------u-4500", "LNG": "eng"}