{"IDN": "000030060", "001": "000030060", "002": "20161230", "005": "20161230201038", "008": "060222s1000------------r-----000-0-eng-d", "040": {"a": "IFIN-HH"}, "080": {"a": "539.143.44"}, "1001": {"L": "000017536", "a": "Lucken, E.A.C."}, "24510": {"a": "Nuclear quadrupole coupling constants", "c": "E.a.c. lucken"}, "260": {"a": "London", "b": "Academic Press", "c": "1969"}, "300": {"a": "X + 360P."}, "852": {"a": "30488", "c": "539"}, "CAT": {"a": "Sys", "c": "20111005", "h": "160405"}, "FMT": "BK", "LDR": "-----nam--22------i-4500", "LNG": "eng"}