{"IDN": "000002031", "001": "000002031", "002": "20161230", "005": "20161230201024", "008": "060222s1000------------r-----000-0-eng-d", "100": {"L": "000000909", "a": "Gjaerevoll, Olav."}, "245": {"a": "Botanical investigations in central alaska, especially in the white mountains. part i.pteridophytes and monocotyledones."}, "260": {"a": "Trindhein, I Kommis.Hos F.Bruns Bokhandel, 1958. 74 P."}, "490": {"a": "Det Kgl Norske Videnskabers Selskabs Skrifter 1958."}, "852": {"a": "6143"}, "FMT": "BK", "LDR": "-----nam--22------i-4500", "LNG": "eng"}