{"IDN": "000054497", "001": "000054497", "002": "20161230", "005": "20170106155137", "008": "120111s1000------------r-----000-0-rus-d", "040": {"a": "IFIN-HH"}, "041": {"a": "rus"}, "080": {"a": "539.125.5"}, "1001": {"L": "000034804", "a": "Kaipov, D. K."}, "24510": {"a": "Ulitraholodnie neitroni", "c": "D.K. Kaipov"}, "260": {"a": "Alma-Ata", "b": "Nauka", "c": "1985"}, "300": {"a": "112 p."}, "852": {"a": "72777", "c": "539.12"}, "CAT": {"a": "SYS", "c": "20170106", "h": "155137"}, "FMT": "BK", "LDR": "-----nam--22------u-4500", "LNG": "rus"}