{"IDN": "000037571", "001": "000037571", "002": "20161230", "005": "20170102170827", "008": "060222s1000------------r-----000-0-eng-d", "040": {"a": "IFIN-HH"}, "080": {"a": "535(082.1)"}, "1001": {"L": "000030899", "a": "Wolf, Emil"}, "24510": {"a": "Progress in optics. Vol. VIII.", "c": "Emil Wolf (Ed.) J.W. Goodman, G.A. Fry, H.Z. Cummins, H.L. Swinney, A. Musset, A. Thelen, H. Risken, T. Yamamoto, L. Levi, C.L. Mehta (Contributors)"}, "260": {"a": "London", "b": "North-Holland Publishing Company"}, "7001": {"L": "000041280", "a": "Mehta, C.L.", "e": "Contributor"}, "787": {"a": "Vol. VIII.", "d": "1970", "h": "458 p."}, "852": {"a": "16567", "c": "535"}, "CAT": {"a": "SYS", "c": "20170102", "h": "170827"}, "FMT": "BK", "LDR": "-----nam--22------i-4500", "LNG": "eng"}