{"IDN": "000053132", "001": "000053132", "002": "20161230", "005": "20161230201051", "008": "110106s1000------------r-----000-0-eng-d", "020": {"a": "1563965410"}, "040": {"a": "IFIN-HH"}, "080": {"a": "539.12:539.1076(063)"}, "1001": {"L": "000031663", "a": "Tajima, T."}, "24510": {"a": "The future of accelerator physics", "b": "The tamura symposium proceedings, austin, tx november 1994", "c": "T. TAJIMA (Ed.)"}, "260": {"a": "Woodbury, New York", "b": "American Institute Of Physics", "c": "1996"}, "300": {"a": "459P."}, "490": {"a": "Aip Conference Proceedings", "v": "Vol. 356"}, "852": {"a": "81556", "c": "539.12"}, "CAT": {"a": "Sys", "c": "20110106", "h": "144405"}, "FMT": "BK", "LDR": "-----nam--22------u-4500", "LNG": "eng"}