{"IDN": "000043859", "001": "000043859", "002": "20161230", "005": "20161230201044", "008": "060222s1000------------r-----000-0-eng-d", "040": {"a": "IFIN-HH"}, "080": {"a": "537.533.3"}, "1001": {"L": "000024637", "a": "Sturrock, P.A."}, "24510": {"a": "Static and dynamic electron optics", "b": "An account of focusing in lens, deflector and accelerator", "c": "P.a. strurrock"}, "260": {"a": "Cambridge", "b": "The University Press", "c": "1955"}, "300": {"a": "X+240P."}, "490": {"a": "Cambridge Monographs On Mechanics And Applied Mathematics"}, "852": {"a": "10394", "c": "537.533.3"}, "CAT": {"a": "Sys", "c": "20110831", "h": "124538"}, "FMT": "BK", "LDR": "-----nam--22------i-4500", "LNG": "eng"}