{"IDN": "000045457", "001": "000045457", "002": "20161230", "005": "20170103010935", "008": "060222s1000------------r-----000-0-rus-d", "040": {"a": "IFIN-HH"}, "041": {"a": "rus"}, "080": {"a": "53"}, "1001": {"L": "000025251", "a": "Cavaleru, Al."}, "24510": {"a": "Tehnici in fizica aplicata. Manual pentru licee de matematica-fizica cu profil de fizica-electrotehnica clasa a XI-a.", "c": "Al. Cavaleru, Marieta Nicolae, Leon Grigorescu, Adriana Teodoru"}, "260": {"a": "Bucuresti", "b": "Editura Didactica Si Pedagogica", "c": "1980"}, "300": {"a": "332 p."}, "7001": {"L": "000041438", "a": "Teodoru, Adriana"}, "852": {"a": "79653", "c": "53"}, "CAT": {"a": "SYS", "c": "20170103", "h": "010935"}, "FMT": "BK", "LDR": "-----nam--22------i-4500", "LNG": "rus"}