{"IDN": "000045569", "001": "000045569", "002": "20161230", "005": "20161230201045", "008": "060222s1000------------r-----000-0-eng-d", "040": {"a": "IFIN-HH"}, "080": {"a": "539.171:539.186.2"}, "1001": {"L": "000025309", "a": "Turkenburg, Wilhelmus Cornelius"}, "24510": {"a": "Surface layer analysis by medium energy ion scattering", "b": "Dissertation", "c": "Wilhelmus cornelius turkenburg"}, "260": {"a": "Amsterdam1", "b": "Universitat", "c": "1976"}, "300": {"a": "139P."}, "852": {"a": "47319", "c": "539.17"}, "CAT": {"a": "Sys", "c": "20120618", "h": "170653"}, "FMT": "BK", "LDR": "-----nam--22------i-4500", "LNG": "eng"}