{"IDN": "000033419", "001": "000033419", "002": "20161230", "005": "20161230201039", "008": "060222s1000------------r-----000-0-fre-d", "040": {"a": "IFIN-HH"}, "041": {"a": "fre"}, "080": {"a": "539.1.073.5(043):539.172.5(043)"}, "1001": {"L": "000034236", "a": "Massonnet, Louis"}, "24510": {"a": "Etude des reactions pi+2p sur quelques noyaux legers a l'aide d'un systeme de chambres a etincelles automatiques", "b": "These", "c": "Louis massonnet"}, "260": {"a": "Paris", "b": "Univerisite", "c": "1969"}, "300": {"a": "/PAG.DIF./"}, "852": {"a": "49431", "c": "539.1.07:539.1.08"}, "CAT": {"a": "Sys", "c": "20111026", "h": "100847"}, "FMT": "BK", "LDR": "-----nam--22------i-4500", "LNG": "fre"}