{"IDN": "000028393", "001": "000028393", "002": "20161230", "005": "20161230201037", "008": "060222s1000------------r-----000-0-fre-d", "040": {"a": "IFIN-HH"}, "041": {"a": "fre"}, "080": {"a": "539.171.16(043)"}, "1001": {"L": "000016594", "a": "Lemos, Orlando F."}, "24510": {"a": "Diffusion elastique de particules alpha de 21 a 29,6 mev sur des noyaux de la region ti-zn", "b": "These", "c": "Orlando f. lemos"}, "260": {"a": "Paris", "b": "Universite", "c": "1972"}, "300": {"a": "107P."}, "852": {"a": "40350", "c": "539.17"}, "CAT": {"a": "Sys", "c": "20120611", "h": "151955"}, "FMT": "BK", "LDR": "-----nam--22------i-4500", "LNG": "fre"}