{"IDN": "000054870", "001": "000054870", "002": "20161230", "005": "20161230201051", "008": "120625s1000------------r-----000-0-fre-d", "040": {"a": "IFIN-HH"}, "041": {"a": "fre"}, "080": {"a": "539.172.3(043)"}, "1001": {"L": "000036091", "a": "Falvard, Alain"}, "24510": {"a": "Etude de la production de paires de particules chargees dans l'interaction photon-photon aupres des anneaux de collisions dci d'orsay", "b": "These", "c": "Alain falvard"}, "260": {"a": "Clermont-ferrand", "b": "Universite", "c": "1983"}, "300": {"a": "232P. + ANEXES"}, "852": {"a": "72433", "c": "539.17"}, "CAT": {"a": "Sys", "c": "20120625", "h": "100058"}, "FMT": "BK", "LDR": "-----nam--22------u-4500", "LNG": "fre"}