{"IDN": "000033816", "001": "000033816", "002": "20161230", "005": "20161230201039", "008": "060222s1000------------r-----000-0-fre-d", "040": {"a": "IFIN-HH"}, "041": {"b": "fre"}, "080": {"a": "52-732:524.1(043)"}, "1001": {"L": "000019629", "a": "Montmerle, Thierry"}, "24510": {"a": "Existe-t-il un rayonnement cosmique cosmologique?", "b": "These", "c": "Thierry montmerle"}, "260": {"a": "Paris", "b": "Universite", "c": "1977"}, "300": {"a": "394P."}, "852": {"a": "48505", "c": "521/522"}, "CAT": {"a": "Sys", "c": "20130826", "h": "181102"}, "FMT": "BK", "LDR": "-----nam--22------i-4500", "LNG": "fre"}