{"IDN": "000009599", "001": "000009599", "002": "20161230", "005": "20161230201028", "008": "060222s1000------------r-----000-0-fre-d", "040": {"a": "IFIN-HH"}, "041": {"a": "fre"}, "080": {"a": "539.16"}, "1001": {"L": "000035654", "a": "Briere, Michel"}, "24510": {"a": "Mesures en radioactivite", "b": "Manuel pratique d'utilisation des rayons nucleaires", "c": "Michel briere, bernard jouve, robert paulin"}, "260": {"a": "Paris", "b": "Hermann", "c": "1970"}, "300": {"a": "261 P."}, "490": {"a": "Actualites Scientifiques Et Industrielles, 1325"}, "7001": {"L": "000040180", "a": "Paulin, Robert"}, "852": {"a": "33951", "c": "539.16"}, "CAT": {"a": "Sys", "c": "20120515", "h": "100928"}, "FMT": "BK", "LDR": "-----nam--22------i-4500", "LNG": "fre"}