{"IDN": "000050430", "001": "000050430", "002": "20161230", "003": "81853", "005": "20161230201048", "008": "070322s1000------------r-----000-0-eng-d", "020": {"a": "9027721416"}, "040": {"a": "IFIN-HH"}, "080": {"a": "512.54:530.145:539.12"}, "1001": {"L": "000010366", "a": "Kim, Y.S. /S.A./"}, "24510": {"a": "Theory and applications of the poincare group", "c": "Y.s. kim ; marilyn e. noz"}, "260": {"a": "Dordrecht", "b": "Publishing Company", "c": "1986"}, "300": {"a": "331 p."}, "490": {"a": "Fundamental Theories Of Physics"}, "7001": {"L": "000031931", "a": "Noz, Marilyn E."}, "852": {"a": "81853", "c": "519.4/5"}, "CAT": {"a": "Sys", "c": "20120508", "h": "092915"}, "FMT": "BK", "LDR": "-----nam--22------u-4500", "LNG": "eng"}