{"IDN": "000016778", "001": "000016778", "002": "20161230", "005": "20170210001529", "008": "060222s1000------------r-----000-0-eng-d", "100": {"L": "000010466", "a": "Campeanu, Aurel"}, "245": {"a": "Masini electrice. Probleme fundamentale, speci ale si de functionare optimala"}, "260": {"a": "Craiova", "b": "Scrisul Romanesc", "c": "1988"}, "300": {"a": "603 p."}, "852": {"a": "621.313"}, "CAT": {"a": "SYS", "c": "20170210", "h": "001529"}, "FMT": "BK", "LDR": "-----nam--22------i-4500", "LNG": "eng"}