{"IDN": "000028408", "001": "000028408", "002": "20161230", "005": "20161230201037", "008": "060222s1000------------r-----000-0-eng-d", "100": {"L": "000016605", "a": "Langbein R., Werkmeister G."}, "245": {"a": "Elektrische messgerate. genauigkeit und einflussgrossen. 3. neubearbeitet auflage."}, "260": {"a": "Leipzig, Akademische Verlagsgeselschaft, 1959, Xii + 251p., 208fig."}, "490": {"a": "Technisch-physikalische Monographien."}, "852": {"a": "6821"}, "FMT": "BK", "LDR": "-----nam--22------i-4500", "LNG": "eng"}