{"IDN": "000055535", "001": "000055535", "002": "20161230", "005": "20161230201052", "008": "130220s1000------------r-----000-0-eng-d", "040": {"a": "IFIN-HH"}, "080": {"a": "621.52:413"}, "1001": {"L": "000008165", "a": "Bibbero, Robert J."}, "24510": {"a": "Dictionary pf automatic control", "b": "With a foreword by theodore k. steele", "c": "Robert j. bibbero"}, "260": {"a": "New York", "b": "Reinhold Publishing Corporation", "c": "1960"}, "300": {"a": "282P."}, "490": {"a": "Automatic Control Library"}, "852": {"a": "D.215", "c": "SLT"}, "CAT": {"a": "Sys", "c": "20130220", "h": "123322"}, "FMT": "BK", "LDR": "-----nam--22------u-4500", "LNG": "eng"}