{"IDN": "000025233", "001": "000025233", "002": "20161230", "005": "20170102234036", "008": "060222s1000------------r-----000-0-eng-d", "080": {"a": "621.385"}, "100": {"L": "000014390", "a": "Ionescu, Cezar"}, "245": {"a": "Catalog de tuburi electronice"}, "260": {"a": "Bucuresti", "b": "Editura Tehnica", "c": "1967"}, "300": {"a": "666 p."}, "700": {"L": "000015009", "a": "Savescu, Ana"}, "852": {"a": "27212"}, "CAT": {"a": "SYS", "c": "20170102", "h": "234036"}, "FMT": "BK", "LDR": "-----nam--22------i-4500", "LNG": "eng"}