{"IDN": "000009664", "001": "000009664", "002": "20161230", "005": "20161230201028", "008": "060222s1000------------r-----000-0-eng-d", "040": {"a": "IFIN-HH"}, "080": {"a": "539.2"}, "1001": {"L": "000036581", "a": "Pincherle, L."}, "24510": {"a": "Electronic energy bands in solids", "c": "L. pincherle"}, "260": {"a": "London", "b": "Macdonald", "c": "1971"}, "300": {"a": "VI+196P."}, "852": {"a": "36635", "c": "539.2"}, "CAT": {"a": "Sys", "c": "20121019", "h": "143908"}, "FMT": "BK", "LDR": "-----nam--22------i-4500", "LNG": "eng"}