{"IDN": "000022449", "001": "000022449", "002": "20161230", "005": "20161230201034", "008": "060222s1000------------r-----000-0-eng-d", "040": {"a": "IFIN-HH"}, "080": {"a": "621.3.018"}, "1001": {"L": "000013454", "a": "Hayashi, Chihiro"}, "24510": {"a": "Nonlinear oscillations in physical systems.", "c": "Chihiro Hayashi"}, "260": {"a": "New York, Mcgraw-hill Book Co., 1964"}, "300": {"a": "XII + 392 P."}, "490": {"a": "Mcgraw-hill Electrical And Electronic Engineering Series."}, "852": {"a": "21678", "c": "531"}, "CAT": {"a": "Sys", "c": "20100622", "h": "145014"}, "FMT": "BK", "LDR": "-----nam--22------i-4500", "LNG": "eng"}