{"IDN": "000001580", "001": "000001580", "002": "20161230", "005": "20161230201024", "008": "060222s1000------------r-----000-0-eng-d", "080": {"a": "621.039.54-42"}, "100": {"L": "000000605", "a": "Freund,George. A"}, "245": {"a": "Materials for control rod drive mechanisms. an aec monograph."}, "260": {"a": "New York, Rowman And Littlefield, Inc,. 1963. Viii + 209 P."}, "490": {"a": "American Society For Metals"}, "852": {"a": "19787"}, "FMT": "BK", "LDR": "-----nam--22------i-4500", "LNG": "eng"}