{"IDN": "000056597", "001": "000056597", "002": "20161230", "005": "20161230201052", "008": "160325s1000------------r-----000-0-eng-d", "040": {"a": "IFIN-HH"}, "080": {"a": "53"}, "1001": {"L": "000014349", "a": "Hodgson, P.E."}, "24510": {"a": "Oxford Kinematical Tables Vol. 4. Negative Pion + Proton to Neutral Lambda + Neutral K up to 30,000 MeV", "c": "P.E. Hodgson, R.N. Maddison"}, "260": {"a": "Oxford", "b": "National Institute for Research in Nuclear Science", "c": "1961"}, "300": {"a": "ix+110p.+suppl."}, "7001": {"L": "000039816", "a": "Maddison, R.N."}, "852": {"a": "19558", "c": "53.081"}, "CAT": {"a": "Sys", "c": "20160325", "h": "124113"}, "FMT": "BK", "LDR": "-----nam--22------u-4500", "LNG": "eng"}