{"IDN": "000019489", "001": "000019489", "002": "20161230", "005": "20161230201033", "008": "060222s1000------------r-----000-0-eng-d", "040": {"a": "IFIN-HH"}, "080": {"a": "539.12.01(061.3):530.12(061.3)"}, "1001": {"L": "000011788", "a": "Svartholm, Nils"}, "24510": {"a": "Elementary particle theory. relativistic groups and analyticity", "b": "Proceedings of the eighth nobel symposium held may 19-25, 1968 at aspenasgarden, lerum, in the county of alvsborg, sweden", "c": "Nils svartholm (edd.)"}, "260": {"a": "Stockholm", "b": "Almqvist & Wiksell", "c": "1968"}, "300": {"a": "399 P."}, "490": {"a": "Proceedings. Nobel Symposium.", "v": "No. 8"}, "852": {"a": "39636", "c": "539.12"}, "CAT": {"a": "Sys", "c": "20111123", "h": "123555"}, "FMT": "BK", "LDR": "-----nam--22------i-4500", "LNG": "eng"}