{"IDN": "000007647", "001": "000007647", "002": "20161230", "005": "20161230201027", "008": "060222s1000------------r-----000-0-eng-d", "080": {"a": "621.318.124:621.382:621.315.592"}, "245": {"a": "Cercetari si metode privind parametrii caracte ristici la substantele noi semiconductoare (ox izi ferite, etc) in jurul punctului curie (fer omagnetic si feroelectric)"}, "260": {"a": "Bucuresti, Institutul De Documentare Tehnica, 1964: 11 P."}, "852": {"a": "D.1157"}, "FMT": "BK", "LDR": "-----nam--22------i-4500", "LNG": "eng"}