{"IDN": "000017362", "001": "000017362", "002": "20161230", "005": "20170127225249", "008": "060222s1000------------r-----000-0-eng-d", "100": {"L": "000010651", "a": "Cotaescu, Ion I."}, "245": {"a": "Gravity, Theoretical Physics And Computers"}, "260": {"a": "Timisoara", "b": "Editura Mirton", "c": "1997"}, "300": {"a": "112 p."}, "490": {"a": "Proceedings"}, "653": {"a": "973-578-"}, "700": {"L": "000010863", "a": "Vulcanov, Dumitru N."}, "852": {"a": "530.12(061.3)"}, "CAT": {"a": "SYS", "c": "20170127", "h": "225249"}, "FMT": "BK", "LDR": "-----nam--22------i-4500", "LNG": "eng"}