{"IDN": "000045825", "001": "000045825", "002": "20161230", "005": "20161230201045", "008": "060222s1000------------r-----000-0-eng-d", "080": {"a": "516(076)"}, "100": {"L": "000025452", "a": "Tuberbiller,O.N."}, "245": {"a": "Probleme si exercitii de geometrie analitica."}, "260": {"a": "Bucuresti, Ed.Tehnica, 1952."}, "300": {"a": "309 P."}, "700": {"L": "000028845", "a": "O. N. Tuberbiller"}, "852": {"a": "2157", "c": "515/516"}, "CAT": {"a": "Sys", "c": "20080610", "h": "104538"}, "FMT": "BK", "LDR": "-----nam--22------i-4500", "LNG": "eng"}