{"IDN": "000053513", "001": "000053513", "002": "20161230", "005": "20161230201051", "008": "110411s1000------------r-----000-0-eng-d", "020": {"a": "0412039710"}, "040": {"a": "IFIN-HH"}, "080": {"a": "57"}, "1001": {"L": "000032275", "a": "Ahmad, Sami"}, "24510": {"a": "Oxidative stress and antioxidant defenses in biology", "b": "Sami ahmad (ed.)"}, "260": {"a": "New York", "b": "Chapman & Hall", "c": "1995"}, "300": {"a": "457P."}, "650 4": {"L": "000000696", "a": "Antioxidants"}, "852": {"a": "80281", "c": "57"}, "CAT": {"a": "Sys", "c": "20110411", "h": "083308"}, "FMT": "BK", "LDR": "-----nam--22------u-4500", "LNG": "eng"}