{"IDN": "000012986", "001": "000012986", "002": "20161230", "005": "20161230201030", "008": "060222s1000------------r-----000-0-eng-d", "020": {"a": "0706515811"}, "040": {"a": "IFIN-HH"}, "080": {"a": "537.84"}, "1001": {"L": "000008170", "a": "Branover, Herman"}, "24510": {"a": "Magnetohydrodynamic flow in ducts", "c": "Herman branover"}, "260": {"a": "New York", "b": "John Wiley & Sons", "c": "1978"}, "300": {"a": "XII + 290 P."}, "852": {"a": "46936", "c": "538.4"}, "CAT": {"a": "Sys", "c": "20110920", "h": "124459"}, "FMT": "BK", "LDR": "-----nam--22------i-4500", "LNG": "eng"}