{"IDN": "000005321", "001": "000005321", "002": "20161230", "005": "20161230201026", "008": "060222s1000------------r-----000-0-eng-d", "080": {"a": "517.512.2"}, "100": {"L": "000003212", "a": "Bochner Salomon"}, "245": {"a": "Lectures on fourier integrals. with an au thor`s suppliment on monotonic functions, sti eltjes integrals and harmonic analysis."}, "260": {"a": "Princeton University Press, 1959. 333 P."}, "490": {"a": "Annals Of Mathematics Studies"}, "852": {"a": "13404"}, "FMT": "BK", "LDR": "-----nam--22------i-4500", "LNG": "eng"}